tasker.py
tasker-0.3.dist-info/LICENSE
tasker-0.3.dist-info/WHEEL
tasker-0.3.dist-info/METADATA
tasker-0.3.dist-info/RECORD
