Metadata-Version: 2.1
Name: tasker
Version: 0.3
Summary: Organizer for project's scripts
Author-email: Vyacheslav Rafalskiy <rafalskiy@gmail.com>
Requires-Python: >=3.6
Classifier: License :: OSI Approved :: MIT License
Classifier: Programming Language :: Python :: 3 :: Only
Classifier: Intended Audience :: Developers
Classifier: Operating System :: OS Independent
Project-URL: Home, https://github.com/s4g/tasker
